{
    "header": {
        "title": "Cho Thuê Mặt Bằng, Văn Phòng Kinh Doanh, Giá Rẻ, Mới Nhất 2023",
        "description": "Có 2.860 tin đăng cho thuê mặt bằng, văn phòng kinh doanh. Giá rẻ, gần chợ, trường học, tiện mở quán ăn, cafe. Đăng tin mặt bằng, văn phòng hiệu quả tại Phongtro123.com"
    },
    "body": [
        {
            "images": [
                "https://pt123.cdn.static123.com/images/thumbs/900x600/fit/2023/07/27/9cd88ca0-66c5-4315-a57a-d044eacbaee9_1690432044.jpg",
                "https://pt123.cdn.static123.com/images/thumbs/900x600/fit/2023/07/27/0e0eb193-2e28-42d8-a433-52b7c92a5299_1690432027.jpg",
                "https://pt123.cdn.static123.com/images/thumbs/900x600/fit/2023/07/27/834eb310-f5ff-4a08-9157-58ed6c3377e6_1690432037.jpg",
                "https://pt123.cdn.static123.com/images/thumbs/900x600/fit/2023/07/27/881b1823-ba96-411b-bb2d-5e49b285f9f8_1690432019.jpg",
                "https://pt123.cdn.static123.com/images/thumbs/900x600/fit/2023/07/27/1fb3cd96-da57-4aab-b895-3188a1523272_1690432019.jpg",
                "https://pt123.cdn.static123.com/images/thumbs/900x600/fit/2023/07/27/21f80eb5-b032-44bf-bab2-4210fbdf89c7_1690432023.jpg",
                "https://pt123.cdn.static123.com/images/thumbs/900x600/fit/2023/07/27/9bc90c6d-d20c-4524-a9f0-48589ec08c62_1690432025.jpg",
                "https://pt123.cdn.static123.com/images/thumbs/900x600/fit/2023/07/27/5c640ce1-9e5d-4fbc-9f2b-97c262fa7548_1690432030.jpg",
                "https://pt123.cdn.static123.com/images/thumbs/900x600/fit/2023/07/27/e6171997-abfd-4693-97e4-52ddd7b1fb3f_1690432033.jpg",
                "https://pt123.cdn.static123.com/images/thumbs/900x600/fit/2023/07/27/9cd88ca0-66c5-4315-a57a-d044eacbaee9_1690432044.jpg"
            ],
            "header": {
                "title": "Mặt Bằng kinh doanh online, tạp hoá nhỏ,kho hàng có gác ở lại",
                "star": "4",
                "class": {
                    "content": "Chuyên mục: Cho thuê mặt bằng, văn phòng Quận Gò Vấp",
                    "classType": "Cho thuê mặt bằng, văn phòng Quận Gò Vấp"
                },
                "address": "Địa chỉ: 206/20 20, Phường 5, Quận Gò Vấp, Hồ Chí Minh",
                "attributes": {
                    "price": "4 triệu/tháng",
                    "acreage": "25m2",
                    "published": "Hôm nay",
                    "hashtag": "626777"
                }
            },
            "mainContent": {
                "header": "Thông tin mô tả",
                "content": [
                    "Mặt Bằng Gò Vấp gần phan văn trị,chợ gò vấp,phạm văn đồng",
                    "-Mặt Bằng có phòng gác ở lại phù hợp kinh doanh online,tạp hoá nhỏ, làm kho .",
                    "206/20 đường D20 , phường 5, Quận Gò Vấp. ( chạy dọc đường Dương Quảng Hàm rẻ vào D20)",
                    "️Giá4tr/ tháng, cọc 1 tháng, hợp đồng1 năm",
                    "Phòng cửa sổ hướng ra bờ sông rộng thoáng, đẹp view chill chill .",
                    "Nội thất gồm có máy lạnh, nệm, tủ quần áo ,toilet riêng trong phòng.",
                    "Máy giặt chung , sân thượng phơi đồ rộng thoáng, hầm để xe rộng!",
                    "Ra vào cửa vân tay, thang máy, giờ giấc tự do , bảo vệ 24/24..",
                    "Các chi phí",
                    "Điện 4.000vnd/1kw",
                    "Nước 50k 1 người / tháng",
                    "Dịch vụ 100k 1 người / tháng",
                    "wifi 50k 1 người/ trên tháng",
                    "Liên hệ để được tư vấn và xem phòng trực tiếp : 0899455299 - 0974188183 (ALinh)",
                    "Be Home - Đảm bảo môi trường sống tốt nhất dành cho bạn.",
                    "------------"
                ]
            },
            "overview": {
                "header": "Đặc điểm tin đăng",
                "content": [
                    {
                        "name": "Mã tin:",
                        "content": "#626777"
                    },
                    {
                        "name": "Khu vực",
                        "content": "Cho thuê mặt bằng, văn phòng Hồ Chí Minh"
                    },
                    {
                        "name": "Loại tin rao:",
                        "content": "Cho thuê mặt bằng, văn phòng"
                    },
                    {
                        "name": "Đối tượng thuê:",
                        "content": "Tất cả"
                    },
                    {
                        "name": "Gói tin:",
                        "content": "Tin VIP 1"
                    },
                    {
                        "name": "Ngày đăng:",
                        "content": "Thứ 2, 13:14 11/09/2023"
                    },
                    {
                        "name": "Ngày hết hạn:",
                        "content": "Thứ 5, 13:14 21/09/2023"
                    }
                ]
            },
            "contact": {
                "header": "Thông tin liên hệ",
                "content": [
                    {
                        "name": "Liên hệ:",
                        "content": "Be Home"
                    },
                    {
                        "name": "Điện thoại:",
                        "content": "0974188183"
                    },
                    {
                        "name": "Zalo",
                        "content": "0974188183"
                    }
                ]
            }
        },
        {
            "images": [
                "https://pt123.cdn.static123.com/images/thumbs/900x600/fit/2023/09/16/z4697962794711-59c47d7d3f85a94ac9b1ad49aa1535a7_1694835502.jpg",
                "https://pt123.cdn.static123.com/images/thumbs/900x600/fit/2023/09/16/z4697962794597-89fb58220b55032f0bb5f13116c6839e_1694835502.jpg",
                "https://pt123.cdn.static123.com/images/thumbs/900x600/fit/2023/09/16/z4697962768611-9eed5ced06e58e0fda0b24b2bf771d72_1694835500.jpg",
                "https://pt123.cdn.static123.com/images/thumbs/900x600/fit/2023/09/16/z4697962773016-be8165664b8a26d14c273e1664c4699b_1694835500.jpg",
                "https://pt123.cdn.static123.com/images/thumbs/900x600/fit/2023/09/16/z4697962794711-59c47d7d3f85a94ac9b1ad49aa1535a7_1694835502.jpg",
                "https://pt123.cdn.static123.com/images/thumbs/900x600/fit/2023/09/16/z4697962794597-89fb58220b55032f0bb5f13116c6839e_1694835502.jpg"
            ],
            "header": {
                "title": "Mặt bằng kinh doanh hoặc để ở quận 7",
                "class": {
                    "content": "Chuyên mục: Cho thuê mặt bằng, văn phòng Quận 7",
                    "classType": "Cho thuê mặt bằng, văn phòng Quận 7"
                },
                "address": "Địa chỉ: 793/39A Đường Trần Xuân Soạn, Phường Tân Hưng, Quận 7, Hồ Chí Minh",
                "attributes": {
                    "price": "5.5 triệu/tháng",
                    "acreage": "20m2",
                    "published": "2 ngày trước",
                    "hashtag": "635604"
                }
            },
            "mainContent": {
                "header": "Thông tin mô tả",
                "content": [
                    "Mặt bằng kinh doanh có thể ở tại 793/39A trần xuân soạn, quận 7 tphcm",
                    "Giá 5tr5",
                    "điện 3k5 nước 20k/m3",
                    "để ở dịch vụ 100k/người.",
                    "Nằm ngay mặt hẻm lớn!"
                ]
            },
            "overview": {
                "header": "Đặc điểm tin đăng",
                "content": [
                    {
                        "name": "Mã tin:",
                        "content": "#635604"
                    },
                    {
                        "name": "Khu vực",
                        "content": "Cho thuê mặt bằng, văn phòng Hồ Chí Minh"
                    },
                    {
                        "name": "Loại tin rao:",
                        "content": "Cho thuê mặt bằng, văn phòng"
                    },
                    {
                        "name": "Đối tượng thuê:",
                        "content": "Tất cả"
                    },
                    {
                        "name": "Gói tin:",
                        "content": "Tin thường"
                    },
                    {
                        "name": "Ngày đăng:",
                        "content": "Thứ 7, 10:38 16/09/2023"
                    },
                    {
                        "name": "Ngày hết hạn:",
                        "content": "Thứ 5, 10:38 21/09/2023"
                    }
                ]
            },
            "contact": {
                "header": "Thông tin liên hệ",
                "content": [
                    {
                        "name": "Liên hệ:",
                        "content": "nguyễn hữu thế"
                    },
                    {
                        "name": "Điện thoại:",
                        "content": "0906844140"
                    },
                    {
                        "name": "Zalo",
                        "content": "0906844140"
                    }
                ]
            }
        },
        {
            "images": [
                "https://pt123.cdn.static123.com/images/thumbs/900x600/fit/2023/09/15/z4696961318562-a258fdfe049700aa5c5bef38412ab096_1694788695.jpg",
                "https://pt123.cdn.static123.com/images/thumbs/900x600/fit/2023/09/15/z4696961307415-764af5caa3ac9ebf4b935bae90a4dc3d_1694788692.jpg",
                "https://pt123.cdn.static123.com/images/thumbs/900x600/fit/2023/09/15/z4696961307906-872c0799a92ea69739a2ba38b51be335_1694788691.jpg",
                "https://pt123.cdn.static123.com/images/thumbs/900x600/fit/2023/09/15/z4696961331696-ec478e2f4c3abc09b09b8a5fd9c51108_1694788699.jpg",
                "https://pt123.cdn.static123.com/images/thumbs/900x600/fit/2023/09/15/z4696961321226-1a8c20b314ab0c6c6d2d42bb8724b0f3_1694788695.jpg",
                "https://pt123.cdn.static123.com/images/thumbs/900x600/fit/2023/09/15/z4696961318562-a258fdfe049700aa5c5bef38412ab096_1694788695.jpg",
                "https://pt123.cdn.static123.com/images/thumbs/900x600/fit/2023/09/15/z4696961307415-764af5caa3ac9ebf4b935bae90a4dc3d_1694788692.jpg"
            ],
            "header": {
                "title": "Chính chủ cho thuê nhà phố Thái Hà",
                "class": {
                    "content": "Chuyên mục: Cho thuê mặt bằng, văn phòng Quận Đống Đa",
                    "classType": "Cho thuê mặt bằng, văn phòng Quận Đống Đa"
                },
                "address": "Địa chỉ: 47 ngõ 178 Phố Thái Hà, Phường Trung Liệt, Quận Đống Đa, Hà Nội",
                "attributes": {
                    "price": "10 triệu/tháng",
                    "acreage": "36m2",
                    "published": "2 ngày trước",
                    "hashtag": "635565"
                }
            },
            "mainContent": {
                "header": "Thông tin mô tả",
                "content": [
                    "Chính chủ cho thuê nhà phố Thái Hà",
                    "Chính chủ cho thuê tầng 1 nhà 47 ngõ 178 phố Thái Hà, diện tích 36m2. Ngõ rộng, có vỉa hè, tiện kinh doanh. Liên hệ chủ nhà, cô Tiền, ĐT: 0983359732."
                ]
            },
            "overview": {
                "header": "Đặc điểm tin đăng",
                "content": [
                    {
                        "name": "Mã tin:",
                        "content": "#635565"
                    },
                    {
                        "name": "Khu vực",
                        "content": "Cho thuê mặt bằng, văn phòng Hà Nội"
                    },
                    {
                        "name": "Loại tin rao:",
                        "content": "Cho thuê mặt bằng, văn phòng"
                    },
                    {
                        "name": "Đối tượng thuê:",
                        "content": "Tất cả"
                    },
                    {
                        "name": "Gói tin:",
                        "content": "Tin miễn phí"
                    },
                    {
                        "name": "Ngày đăng:",
                        "content": "Thứ 6, 21:42 15/09/2023"
                    },
                    {
                        "name": "Ngày hết hạn:",
                        "content": "Thứ 4, 21:42 20/09/2023"
                    }
                ]
            },
            "contact": {
                "header": "Thông tin liên hệ",
                "content": [
                    {
                        "name": "Liên hệ:",
                        "content": "Nguyễn Thị Tiền"
                    },
                    {
                        "name": "Điện thoại:",
                        "content": "0983359732"
                    },
                    {
                        "name": "Zalo",
                        "content": "0983359732"
                    }
                ]
            }
        },
        {
            "images": [
                "https://pt123.cdn.static123.com/images/thumbs/900x600/fit/2021/02/23/z2337737536576-621a6bff31715d60bb0523cdf6b38480_1614076093.jpg",
                "https://pt123.cdn.static123.com/images/thumbs/900x600/fit/2018/09/16/6677212c-c364-4233-9409-2413ed829d17_1537086353.jpg",
                "https://pt123.cdn.static123.com/images/thumbs/900x600/fit/2020/06/05/6156d18d27efdab183fe_1591335562.jpg",
                "https://pt123.cdn.static123.com/images/thumbs/900x600/fit/2020/06/05/682317cde1af1cf145be_1591335565.jpg",
                "https://pt123.cdn.static123.com/images/thumbs/900x600/fit/2020/09/28/z2079496423264-23613f8a04f1520432eae775d6c7e8c5_1601272255.jpg",
                "https://pt123.cdn.static123.com/images/thumbs/900x600/fit/2020/09/28/z2079496423571-0968fceeca99ce51126321594e6ec1a9_1601272255.jpg",
                "https://pt123.cdn.static123.com/images/thumbs/900x600/fit/2020/09/28/z2079496424251-c1d2c6703531945fed7c215d78812db6_1601272258.jpg",
                "https://pt123.cdn.static123.com/images/thumbs/900x600/fit/2020/09/28/z2079496414839-659c0ae36c103df17a273c9947391212_1601272274.jpg",
                "https://pt123.cdn.static123.com/images/thumbs/900x600/fit/2020/09/28/z2079496418594-a3ea669b3770c8112d68354da7c40fc9_1601272274.jpg",
                "https://pt123.cdn.static123.com/images/thumbs/900x600/fit/2020/09/28/z2079496420725-aace85113481e6b96b9f0cee6580af71_1601272276.jpg",
                "https://pt123.cdn.static123.com/images/thumbs/900x600/fit/2020/09/28/z2079496408739-13258281900db64fc88b748cbc5afcb7_1601272284.jpg",
                "https://pt123.cdn.static123.com/images/thumbs/900x600/fit/2021/02/23/z2337737527530-a64cf7f0e47365af482d0a35962c4d91_1614076092.jpg",
                "https://pt123.cdn.static123.com/images/thumbs/900x600/fit/2021/02/23/z2337737527706-9767a2fd2028349d8336985c6a08da00_1614076092.jpg",
                "https://pt123.cdn.static123.com/images/thumbs/900x600/fit/2021/02/23/z2337737530979-a047a8515ae322cc65dc3d4a7cf259d1_1614076093.jpg",
                "https://pt123.cdn.static123.com/images/thumbs/900x600/fit/2021/02/23/z2337737536576-621a6bff31715d60bb0523cdf6b38480_1614076093.jpg",
                "https://pt123.cdn.static123.com/images/thumbs/900x600/fit/2018/09/16/6677212c-c364-4233-9409-2413ed829d17_1537086353.jpg"
            ],
            "header": {
                "title": "Văn phòng mặt tiền đường 60 mét - Khu Trung Sơn cho thuê - giá rẻ 5-6-7tr/tháng",
                "class": {
                    "content": "Chuyên mục: Cho thuê mặt bằng, văn phòng Huyện Bình Chánh",
                    "classType": "Cho thuê mặt bằng, văn phòng Huyện Bình Chánh"
                },
                "address": "Địa chỉ: 109-111 Đường số 8, Xã Bình Hưng, Huyện Bình Chánh, Hồ Chí Minh",
                "attributes": {
                    "price": "5 triệu/tháng",
                    "acreage": "200m2",
                    "published": "3 ngày trước",
                    "hashtag": "270381"
                }
            },
            "mainContent": {
                "header": "Thông tin mô tả",
                "content": [
                    "văn phòng mới tại 109-111 đường Số 08 ngay góc ngã tư đường 9A, khu Trung Sơn giáp ranh quận 7 - cầu Him Lam - Quận 8 - cầu Nguyễn Văn Cừ. Đi về các quận trung tâm Quận 1 - Quận 3 - Quận 5 - Quận 4 rất gần, VP mới hiện đại và giá tốt.",
                    "* Quy mô tòa nhà: 1 trệt + lửng+ 3 tầng.",
                    "Với dịch vụ văn phòng chuyên nghiệp, sang trọng, tất cả đã tích hợp sẵn.",
                    "Cung cấp dịch vụ nội thất cao cấp, thiết kế sang trọng và hiện đại.",
                    "Diện tích cho thuê 20m2, 30m2, 60m2, 100m2.(có phòng họp riêng)",
                    "Giá thuê: 5-6-7tr/tháng đã bao gồm phí quản lý: Dịch vụ lễ tân tiếp khách, vệ sinh, bảo vệ và máy photocopy miễn phí.",
                    "* Bao gồm phòng trống, thiết kế mới theo phong cách khách hàng lựa chọn.",
                    "* Hoặc phòng đã trang bị đầy đủ trang thiết bị cho khách thuê",
                    "- Xuất hóa đơn GTGT văn phòng cho thuê, khấu trừ Thuế doanh nghiệp.",
                    "- Có bãi gửi xe máy, mặt tiền đường 10 mét, xe ô tô lui đến thoải mái, có chỗ đậu xe ô tô rộng rãi",
                    "- Photo, in ấn (trắng đen): Miễn phí (không bao gồm giấy).",
                    "- Trang bị bàn làm việc và tủ hồ sơ tiêu chuẩn theo yêu cầu của khách (có tính phí).",
                    "- Phiên dịch tiếng anh",
                    "Liên hệ => Ms Ngọc",
                    "Địa chỉ: 109-111 đường số 08, khu Trung Sơn, Bình Chánh, thành phố Hồ Chí Minh.",
                    "Vina, zalo: 0366790688",
                    "Email: ngocthuy@gmail.com."
                ]
            },
            "overview": {
                "header": "Đặc điểm tin đăng",
                "content": [
                    {
                        "name": "Mã tin:",
                        "content": "#270381"
                    },
                    {
                        "name": "Khu vực",
                        "content": "Cho thuê mặt bằng, văn phòng Hồ Chí Minh"
                    },
                    {
                        "name": "Loại tin rao:",
                        "content": "Cho thuê mặt bằng, văn phòng"
                    },
                    {
                        "name": "Đối tượng thuê:",
                        "content": "Tất cả"
                    },
                    {
                        "name": "Gói tin:",
                        "content": "Tin thường"
                    },
                    {
                        "name": "Ngày đăng:",
                        "content": "Thứ 6, 17:34 15/09/2023"
                    },
                    {
                        "name": "Ngày hết hạn:",
                        "content": "Thứ 7, 13:07 23/09/2023"
                    }
                ]
            },
            "contact": {
                "header": "Thông tin liên hệ",
                "content": [
                    {
                        "name": "Liên hệ:",
                        "content": "tuyenafc"
                    },
                    {
                        "name": "Điện thoại:",
                        "content": "0366790688"
                    },
                    {
                        "name": "Zalo",
                        "content": "0366790688"
                    }
                ]
            }
        },
        {
            "images": [
                "https://pt123.cdn.static123.com/images/thumbs/900x600/fit/2023/08/30/img-20230830-080006_1693357686.jpg",
                "https://pt123.cdn.static123.com/images/thumbs/900x600/fit/2023/08/30/img-20230830-080004_1693357684.jpg",
                "https://pt123.cdn.static123.com/images/thumbs/900x600/fit/2023/08/30/img-20230830-080008_1693357680.jpg",
                "https://pt123.cdn.static123.com/images/thumbs/900x600/fit/2023/08/30/img-20230830-080011_1693357683.jpg",
                "https://pt123.cdn.static123.com/images/thumbs/900x600/fit/2023/08/30/img-20230830-080010_1693357683.jpg",
                "https://pt123.cdn.static123.com/images/thumbs/900x600/fit/2023/08/30/img-20230830-080002_1693357685.jpg",
                "https://pt123.cdn.static123.com/images/thumbs/900x600/fit/2023/08/30/img-20230830-075958_1693357685.jpg",
                "https://pt123.cdn.static123.com/images/thumbs/900x600/fit/2023/08/30/img-20230830-080006_1693357686.jpg",
                "https://pt123.cdn.static123.com/images/thumbs/900x600/fit/2023/08/30/img-20230830-080004_1693357684.jpg"
            ],
            "header": {
                "title": "Cho thuê VP đường số 7, HBC, Thủ Đức",
                "class": {
                    "content": "Chuyên mục: Cho thuê mặt bằng, văn phòng Quận Thủ Đức",
                    "classType": "Cho thuê mặt bằng, văn phòng Quận Thủ Đức"
                },
                "address": "Địa chỉ: Đường số 7, Phường Hiệp Bình Chánh, Quận Thủ Đức, Hồ Chí Minh",
                "attributes": {
                    "price": "9 triệu/tháng",
                    "acreage": "50m2",
                    "published": "14/09/2023",
                    "hashtag": "634268"
                }
            },
            "mainContent": {
                "header": "Thông tin mô tả",
                "content": [
                    "Cho thuê VP Đường số 7, Phường Hiệp Bình Chánh , Quận Thủ Đức",
                    "Giá: 9tr",
                    "Diện tích: 40m2",
                    "Hiện trạng:",
                    "Có WC riêng, kho chứa hàng 6m2",
                    "Sẵn 1 máy lạnh",
                    "HĐ 1 năm, cọc 2 tháng",
                    "Liên hệ Hoàng Sinh"
                ]
            },
            "overview": {
                "header": "Đặc điểm tin đăng",
                "content": [
                    {
                        "name": "Mã tin:",
                        "content": "#634268"
                    },
                    {
                        "name": "Khu vực",
                        "content": "Cho thuê mặt bằng, văn phòng Hồ Chí Minh"
                    },
                    {
                        "name": "Loại tin rao:",
                        "content": "Cho thuê mặt bằng, văn phòng"
                    },
                    {
                        "name": "Đối tượng thuê:",
                        "content": "Tất cả"
                    },
                    {
                        "name": "Gói tin:",
                        "content": "Tin thường"
                    },
                    {
                        "name": "Ngày đăng:",
                        "content": "Thứ 5, 19:01 14/09/2023"
                    },
                    {
                        "name": "Ngày hết hạn:",
                        "content": "Thứ 3, 19:01 19/09/2023"
                    }
                ]
            },
            "contact": {
                "header": "Thông tin liên hệ",
                "content": [
                    {
                        "name": "Liên hệ:",
                        "content": "Hoàng Sinh"
                    },
                    {
                        "name": "Điện thoại:",
                        "content": "0904553939"
                    },
                    {
                        "name": "Zalo",
                        "content": "0904553939"
                    }
                ]
            }
        },
        {
            "images": [
                "https://pt123.cdn.static123.com/images/thumbs/900x600/fit/2023/09/14/4_1694684948.jpg",
                "https://pt123.cdn.static123.com/images/thumbs/900x600/fit/2023/09/14/1_1694684939.jpg",
                "https://pt123.cdn.static123.com/images/thumbs/900x600/fit/2023/09/14/2_1694684939.jpg",
                "https://pt123.cdn.static123.com/images/thumbs/900x600/fit/2023/09/14/3_1694684941.jpg",
                "https://pt123.cdn.static123.com/images/thumbs/900x600/fit/2023/09/14/4_1694684948.jpg",
                "https://pt123.cdn.static123.com/images/thumbs/900x600/fit/2023/09/14/1_1694684939.jpg"
            ],
            "header": {
                "title": "Cho thuê tầng trệt nhà mặt tiền đường tại địa chỉ số 1D Bình Giã, P.13, Quận Tân Bình",
                "class": {
                    "content": "Chuyên mục: Cho thuê mặt bằng, văn phòng Quận Tân Bình",
                    "classType": "Cho thuê mặt bằng, văn phòng Quận Tân Bình"
                },
                "address": "Địa chỉ: 1D Đường Bình Giã, Phường 13, Quận Tân Bình, Hồ Chí Minh",
                "attributes": {
                    "price": "9 triệu/tháng",
                    "acreage": "26m2",
                    "published": "14/09/2023",
                    "hashtag": "635446"
                }
            },
            "mainContent": {
                "header": "Thông tin mô tả",
                "content": [
                    "Cho thuê tầng trệt nhà mặt tiền đường tại địa chỉ số 1D Bình Giã, P.13, Quận Tân Bình",
                    "- Diện tích sử dụng: 2,6m x 10m",
                    "- Giá: 9,000,000 vnđ",
                    "- Vị trí: Ngay mặt tiền đường Bình Giã; khu vực gần trường học, cty và nhiều xe di chuyển qua lại phù hợp cho công việc kinh doanh, buôn bán,...",
                    "- Có thể dùng làm văn phòng hoặc dùng để kinh doanh các mặt hàng như: làm tóc, bán các mặt hàng đồ khô hợp pháp, kinh doanh quần áo. Không kinh doanh các mặt hàng ăn uống,...",
                    "- Liên hệ SĐT (Zalo): A.Dũng _ 0903965373",
                    "(hoặc C.Huê _ 0965997116)"
                ]
            },
            "overview": {
                "header": "Đặc điểm tin đăng",
                "content": [
                    {
                        "name": "Mã tin:",
                        "content": "#635446"
                    },
                    {
                        "name": "Khu vực",
                        "content": "Cho thuê mặt bằng, văn phòng Hồ Chí Minh"
                    },
                    {
                        "name": "Loại tin rao:",
                        "content": "Cho thuê mặt bằng, văn phòng"
                    },
                    {
                        "name": "Đối tượng thuê:",
                        "content": "Tất cả"
                    },
                    {
                        "name": "Gói tin:",
                        "content": "Tin thường"
                    },
                    {
                        "name": "Ngày đăng:",
                        "content": "Thứ 5, 16:50 14/09/2023"
                    },
                    {
                        "name": "Ngày hết hạn:",
                        "content": "Thứ 5, 16:50 21/09/2023"
                    }
                ]
            },
            "contact": {
                "header": "Thông tin liên hệ",
                "content": [
                    {
                        "name": "Liên hệ:",
                        "content": "Nguyễn Thị Kim Huê"
                    },
                    {
                        "name": "Điện thoại:",
                        "content": "0965997116"
                    },
                    {
                        "name": "Zalo",
                        "content": "0965997116"
                    }
                ]
            }
        },
        {
            "images": [
                "https://pt123.cdn.static123.com/images/thumbs/900x600/fit/2023/09/14/z4655570974984-aba5e3bfbe06224013c233cc2b2ba6b2_1694681274.jpg",
                "https://pt123.cdn.static123.com/images/thumbs/900x600/fit/2023/09/14/z4655570831381-e7d30655ed39c9a531a6f2dc4b199cd9_1694681269.jpg",
                "https://pt123.cdn.static123.com/images/thumbs/900x600/fit/2023/09/14/z4655571007695-9e0085bfa4ba2c649c4e1c64c3982801_1694681267.jpg",
                "https://pt123.cdn.static123.com/images/thumbs/900x600/fit/2023/09/14/z4655571034359-9c664e3885476d12c8e51649ef581305_1694681267.jpg",
                "https://pt123.cdn.static123.com/images/thumbs/900x600/fit/2023/09/14/z4655570865309-eef5e19c3723e27185d5e729b700343b_1694681270.jpg",
                "https://pt123.cdn.static123.com/images/thumbs/900x600/fit/2023/09/14/z4655570907755-f75e04415310be7e16360fc9641bbee3_1694681272.jpg",
                "https://pt123.cdn.static123.com/images/thumbs/900x600/fit/2023/09/14/z4655570941761-b1857560b8fb01794a5d0a0c1171c476_1694681273.jpg",
                "https://pt123.cdn.static123.com/images/thumbs/900x600/fit/2023/09/14/z4655570974984-aba5e3bfbe06224013c233cc2b2ba6b2_1694681274.jpg",
                "https://pt123.cdn.static123.com/images/thumbs/900x600/fit/2023/09/14/z4655570831381-e7d30655ed39c9a531a6f2dc4b199cd9_1694681269.jpg"
            ],
            "header": {
                "title": "Mặt Bằng Sân Thượng ngay Mặt tiền Trường Chinh quận 12 - Cầu Tham Lương - sát Tân Bình",
                "class": {
                    "content": "Chuyên mục: Cho thuê mặt bằng, văn phòng Quận 12",
                    "classType": "Cho thuê mặt bằng, văn phòng Quận 12"
                },
                "address": "Địa chỉ: Đường Trường Chinh, Phường Tân Hưng Thuận, Quận 12, Hồ Chí Minh",
                "attributes": {
                    "price": "16 triệu/tháng",
                    "acreage": "100m2",
                    "published": "14/09/2023",
                    "hashtag": "635434"
                }
            },
            "mainContent": {
                "header": "Thông tin mô tả",
                "content": [
                    "----CHO THUÊ MẶT BẰNG KINH DOANH QUẬN 12 MẶT TIỀN TRƯỜNG CHINH -THAM LƯƠNG -----",
                    "Mặt bằng văn phòng và mặt bằng rooftop sân thượng chung 1 tòa nhà ",
                    "Địa chỉ: Trường Chinh, phường Tân Hưng Thuận, quận 12 - vừa qua cầu Tham Lương",
                    "Mặt bằng văn phòng mặt tiền Trường Chinh : 5m x 10m đã set up cơ bản hỗ trợ sơn sửa làm văn phòng rộng mà giá rẻ so với thị trường",
                    "Mặt bằng sân thượng rooftop cực rộng : 140m2 2 tầng riêng biệt đã set up cơ bản hỗ trợ sơn sửa phù hợp kinh doanh cf, ăn uống",
                    "Giá",
                    "Văn Phòng: 10tr",
                    "Rooftop 18tr",
                    "-> Có thể thương lượng giá cho khách thiện chí",
                    "Vị trí tốt, đông dân cư, nhà sạch sẽ , thoáng, nhà mới,dọn vào kinh doanh ngay",
                    "Cọc: 2 tháng",
                    "Thời hạn thuê: 2-3 năm",
                    "Zalo & Call : 0778.641.231 - gặp Minh để xem trực tiếp"
                ]
            },
            "overview": {
                "header": "Đặc điểm tin đăng",
                "content": [
                    {
                        "name": "Mã tin:",
                        "content": "#635434"
                    },
                    {
                        "name": "Khu vực",
                        "content": "Cho thuê mặt bằng, văn phòng Hồ Chí Minh"
                    },
                    {
                        "name": "Loại tin rao:",
                        "content": "Cho thuê mặt bằng, văn phòng"
                    },
                    {
                        "name": "Đối tượng thuê:",
                        "content": "Tất cả"
                    },
                    {
                        "name": "Gói tin:",
                        "content": "Tin thường"
                    },
                    {
                        "name": "Ngày đăng:",
                        "content": "Thứ 5, 15:49 14/09/2023"
                    },
                    {
                        "name": "Ngày hết hạn:",
                        "content": "Thứ 5, 15:49 21/09/2023"
                    }
                ]
            },
            "contact": {
                "header": "Thông tin liên hệ",
                "content": [
                    {
                        "name": "Liên hệ:",
                        "content": "Hoàng Lê Minh"
                    },
                    {
                        "name": "Điện thoại:",
                        "content": "0778641231"
                    },
                    {
                        "name": "Zalo",
                        "content": "0778641231"
                    }
                ]
            }
        },
        {
            "images": [
                "https://pt123.cdn.static123.com/images/thumbs/900x600/fit/2023/09/14/vp26duonglang-3_1694662445.jpg",
                "https://pt123.cdn.static123.com/images/thumbs/900x600/fit/2023/09/14/vp26duonglang-1-copy_1694662436.jpg",
                "https://pt123.cdn.static123.com/images/thumbs/900x600/fit/2023/09/14/vp26duonglang-2-copy_1694662439.jpg",
                "https://pt123.cdn.static123.com/images/thumbs/900x600/fit/2023/09/14/vp26duonglang-3_1694662445.jpg",
                "https://pt123.cdn.static123.com/images/thumbs/900x600/fit/2023/09/14/vp26duonglang-1-copy_1694662436.jpg"
            ],
            "header": {
                "title": "Cho thuê văn phòng giá rẻ khu vực Ngã Tư Sở, Đống Đa",
                "class": {
                    "content": "Chuyên mục: Cho thuê mặt bằng, văn phòng Quận Đống Đa",
                    "classType": "Cho thuê mặt bằng, văn phòng Quận Đống Đa"
                },
                "address": "Địa chỉ: 26 Đường Láng, Phường Ngã Tư Sở, Quận Đống Đa, Hà Nội",
                "attributes": {
                    "price": "11.5 triệu/tháng",
                    "acreage": "72m2",
                    "published": "14/09/2023",
                    "hashtag": "635396"
                }
            },
            "mainContent": {
                "header": "Thông tin mô tả",
                "content": [
                    "CHO THUÊ VĂN PHÒNG CHÍNH CHỦ TẠI QUẬN ĐỐNG ĐA, HÀ NỘI",
                    "Địa chỉ: 26 Đường Láng, Quận Đống Đa, Hà Nội",
                    "Thông tin về văn phòng:",
                    "Diện tích: 70m2",
                    "Mặt tiền: 5m",
                    "Có vách kính ngăn cách phòng làm việc",
                    "Thuộc tòa nhà 8 tầng đầy đủ dịch vụ tiện nghi",
                    "Tiện ích:",
                    "Chỗ để xe rộng rãi, thoải mái",
                    "Bảo vệ trông coi 24/24 giờ",
                    "Đỗ ô tô",
                    "Thang máy lên xuống",
                    "Dụng cụ và thiết bị có sẵn trong văn phòng:",
                    "Điều hòa",
                    "Internet",
                    "Trần thạch cao",
                    "Thảm trải sàn văn phòng",
                    "Bàn ghế văn phòng",
                    "=> Chỉ việc đến và làm việc mà không cần lo lắng về trang thiết bị.",
                    "Phù hợp sử dụng cho:",
                    "Văn phòng công ty",
                    "Văn phòng đại diện",
                    "Hoạt động du lịch",
                    "Bán hàng online",
                    "Lớp học",
                    "Spa",
                    "Đào tạo",
                    "Và nhiều mục đích khác...",
                    "Cam kết đầy đủ tiện nghi.",
                    "Giá thuê: 12 triệu 500 nghìn đồng/tháng (Có thể thương lượng)",
                    "Liên hệ:",
                    "Zalo hoặc gọi điện thoại số: 0968141940",
                    " "
                ]
            },
            "overview": {
                "header": "Đặc điểm tin đăng",
                "content": [
                    {
                        "name": "Mã tin:",
                        "content": "#635396"
                    },
                    {
                        "name": "Khu vực",
                        "content": "Cho thuê mặt bằng, văn phòng Hà Nội"
                    },
                    {
                        "name": "Loại tin rao:",
                        "content": "Cho thuê mặt bằng, văn phòng"
                    },
                    {
                        "name": "Đối tượng thuê:",
                        "content": "Tất cả"
                    },
                    {
                        "name": "Gói tin:",
                        "content": "Tin thường"
                    },
                    {
                        "name": "Ngày đăng:",
                        "content": "Thứ 5, 10:43 14/09/2023"
                    },
                    {
                        "name": "Ngày hết hạn:",
                        "content": "Thứ 3, 10:43 19/09/2023"
                    }
                ]
            },
            "contact": {
                "header": "Thông tin liên hệ",
                "content": [
                    {
                        "name": "Liên hệ:",
                        "content": "Nguyễn Duy"
                    },
                    {
                        "name": "Điện thoại:",
                        "content": "0968141940"
                    },
                    {
                        "name": "Zalo",
                        "content": "0968141940"
                    }
                ]
            }
        },
        {
            "images": [
                "https://pt123.cdn.static123.com/images/thumbs/900x600/fit/2021/12/07/67-lvl_1638847167.jpg",
                "https://pt123.cdn.static123.com/images/thumbs/900x600/fit/2021/12/07/67-lvl_1638847167.jpg",
                "https://pt123.cdn.static123.com/images/thumbs/900x600/fit/2021/12/07/67-lvl_1638847167.jpg"
            ],
            "header": {
                "title": "Cho thuê cửa hàng tại 67 Lê Văn Lương",
                "class": {
                    "content": "Chuyên mục: Cho thuê mặt bằng, văn phòng Quận Cầu Giấy",
                    "classType": "Cho thuê mặt bằng, văn phòng Quận Cầu Giấy"
                },
                "address": "Địa chỉ: 67 Đường Lê Văn Lương, Phường Trung Hòa, Quận Cầu Giấy, Hà Nội",
                "attributes": {
                    "price": "26 triệu/tháng",
                    "acreage": "50m2",
                    "published": "14/09/2023",
                    "hashtag": "309219"
                }
            },
            "mainContent": {
                "header": "Thông tin mô tả",
                "content": [
                    "Cho thuê cửa hàng tại 67 Lê Văn Lương ngay chân cầu vượt Láng Hạ, diện tích ~50m2, mặt tiền 4.5m, hướng Đông Nam, 1 tầng, cho thuê giá 26tr/tháng. Miễn trung gian, môi giới. Liên hệ chị Yên để xem cửa hàng tại mọi thời gian trong ngày."
                ]
            },
            "overview": {
                "header": "Đặc điểm tin đăng",
                "content": [
                    {
                        "name": "Mã tin:",
                        "content": "#309219"
                    },
                    {
                        "name": "Khu vực",
                        "content": "Cho thuê mặt bằng, văn phòng Hà Nội"
                    },
                    {
                        "name": "Loại tin rao:",
                        "content": "Cho thuê mặt bằng, văn phòng"
                    },
                    {
                        "name": "Đối tượng thuê:",
                        "content": "Tất cả"
                    },
                    {
                        "name": "Gói tin:",
                        "content": "Tin thường"
                    },
                    {
                        "name": "Ngày đăng:",
                        "content": "Thứ 5, 09:45 14/09/2023"
                    },
                    {
                        "name": "Ngày hết hạn:",
                        "content": "Thứ 6, 09:43 29/09/2023"
                    }
                ]
            },
            "contact": {
                "header": "Thông tin liên hệ",
                "content": [
                    {
                        "name": "Liên hệ:",
                        "content": "Nguyen Thi Yen"
                    },
                    {
                        "name": "Điện thoại:",
                        "content": "0366195101"
                    },
                    {
                        "name": "Zalo",
                        "content": "0366195101"
                    }
                ]
            }
        },
        {
            "images": [
                "https://pt123.cdn.static123.com/images/thumbs/900x600/fit/2023/09/12/18_1694507634.jpg",
                "https://pt123.cdn.static123.com/images/thumbs/900x600/fit/2023/09/12/11_1694507631.jpg",
                "https://pt123.cdn.static123.com/images/thumbs/900x600/fit/2023/09/12/1_1694507631.jpg",
                "https://pt123.cdn.static123.com/images/thumbs/900x600/fit/2023/09/12/2_1694507632.jpg",
                "https://pt123.cdn.static123.com/images/thumbs/900x600/fit/2023/09/12/3_1694507633.jpg",
                "https://pt123.cdn.static123.com/images/thumbs/900x600/fit/2023/09/12/4_1694507633.jpg",
                "https://pt123.cdn.static123.com/images/thumbs/900x600/fit/2023/09/12/12_1694507634.jpg",
                "https://pt123.cdn.static123.com/images/thumbs/900x600/fit/2023/09/12/18_1694507634.jpg",
                "https://pt123.cdn.static123.com/images/thumbs/900x600/fit/2023/09/12/11_1694507631.jpg"
            ],
            "header": {
                "title": "Chính chủ cho thuê mặt bằng hẻm xe tải Út Tịch Tân Bình có gác 8,5tr",
                "class": {
                    "content": "Chuyên mục: Cho thuê mặt bằng, văn phòng Quận Tân Bình",
                    "classType": "Cho thuê mặt bằng, văn phòng Quận Tân Bình"
                },
                "address": "Địa chỉ: Đường Út Tịch, Phường 4, Quận Tân Bình, Hồ Chí Minh",
                "attributes": {
                    "price": "8.5 triệu/tháng",
                    "acreage": "50m2",
                    "published": "12/09/2023",
                    "hashtag": "635249"
                }
            },
            "mainContent": {
                "header": "Thông tin mô tả",
                "content": [
                    "CHÍNH CHỦ CHO THUÊ MẶT BẰNG THUẬN TIỆN KINH DOANH",
                    "- Địa chỉ: sát mặt tiền đường Út Tịch P.4 Tân Bình, đường trước nhà rộng 6m, có gác ở lại",
                    "- Diện tích mặt bằng 50m2, có gác ở lại & có wc, lối đi riêng.",
                    "- Khu vực xung quanh có nhiều trường học, công ty, cửa hàng ăn uống, trung tâm thể thao… phù hợp kinh doanh đa ngành nghề.",
                    "- Mặt bằng có vỉa hè rộng.",
                    "- Giá thuê 8.500.000đ, cọc 2 tháng. Giá còn thương lượng cho khách thiện chí thuê lâu dài.",
                    "Mọi chi tiết xin liên hệ Nguyên 0936685539"
                ]
            },
            "overview": {
                "header": "Đặc điểm tin đăng",
                "content": [
                    {
                        "name": "Mã tin:",
                        "content": "#635249"
                    },
                    {
                        "name": "Khu vực",
                        "content": "Cho thuê mặt bằng, văn phòng Hồ Chí Minh"
                    },
                    {
                        "name": "Loại tin rao:",
                        "content": "Cho thuê mặt bằng, văn phòng"
                    },
                    {
                        "name": "Đối tượng thuê:",
                        "content": "Tất cả"
                    },
                    {
                        "name": "Gói tin:",
                        "content": "Tin thường"
                    },
                    {
                        "name": "Ngày đăng:",
                        "content": "Thứ 3, 15:34 12/09/2023"
                    },
                    {
                        "name": "Ngày hết hạn:",
                        "content": "Thứ 4, 15:34 27/09/2023"
                    }
                ]
            },
            "contact": {
                "header": "Thông tin liên hệ",
                "content": [
                    {
                        "name": "Liên hệ:",
                        "content": "Lê Phúc Hạnh Nguyên"
                    },
                    {
                        "name": "Điện thoại:",
                        "content": "0936685539"
                    },
                    {
                        "name": "Zalo",
                        "content": "0936685539"
                    }
                ]
            }
        },
        {
            "images": [
                "https://pt123.cdn.static123.com/images/thumbs/900x600/fit/2023/09/13/z4492395674587-c56376347073ec12322759f9320d1710_1694570726.jpg",
                "https://pt123.cdn.static123.com/images/thumbs/900x600/fit/2023/09/12/z4492395662868-a96a7baea0dd0118a0f8f1cf22267049_1694490238.jpg",
                "https://pt123.cdn.static123.com/images/thumbs/900x600/fit/2023/09/13/z4492395658561-2f1fb49270a046252722960670e98026_1694570720.jpg",
                "https://pt123.cdn.static123.com/images/thumbs/900x600/fit/2023/09/13/z4492395662868-a96a7baea0dd0118a0f8f1cf22267049_1694570720.jpg",
                "https://pt123.cdn.static123.com/images/thumbs/900x600/fit/2023/09/13/z4492395663263-ff857209e7cd4bd304c983c1e584da2f_1694570722.jpg",
                "https://pt123.cdn.static123.com/images/thumbs/900x600/fit/2023/09/13/z4492395665587-77efe992fa9ff5f72a998c5399dc7a6c_1694570723.jpg",
                "https://pt123.cdn.static123.com/images/thumbs/900x600/fit/2023/09/13/z4492395668737-17dbfd970ab04aaaf869a0bc60a676c2_1694570724.jpg",
                "https://pt123.cdn.static123.com/images/thumbs/900x600/fit/2023/09/13/z4492395673473-5af883ba7e03d1c3ee219d58dbc3a542_1694570725.jpg",
                "https://pt123.cdn.static123.com/images/thumbs/900x600/fit/2023/09/13/z4492395674587-c56376347073ec12322759f9320d1710_1694570726.jpg",
                "https://pt123.cdn.static123.com/images/thumbs/900x600/fit/2023/09/12/z4492395662868-a96a7baea0dd0118a0f8f1cf22267049_1694490238.jpg"
            ],
            "header": {
                "title": "Cho thuê văn phòng mặt tiền Nơ Trang Long 60m2 vị trí Cực Đẹp có 2ML sàn rộng",
                "class": {
                    "content": "Chuyên mục: Cho thuê mặt bằng, văn phòng Quận Bình Thạnh",
                    "classType": "Cho thuê mặt bằng, văn phòng Quận Bình Thạnh"
                },
                "address": "Địa chỉ: 219B Đường Nơ Trang Long, Phường 12, Quận Bình Thạnh, Hồ Chí Minh",
                "attributes": {
                    "price": "6 triệu/tháng",
                    "acreage": "60m2",
                    "published": "12/09/2023",
                    "hashtag": "635199"
                }
            },
            "mainContent": {
                "header": "Thông tin mô tả",
                "content": [
                    "Cho thuê văn phòng mặt tiền đường Nơ Trang Long, quận Bình Thạnh - Vị trí đắc địa, tiện nghi đa dạng!",
                    "Dễ Dàng Di Chuyển - Kết Nối Tốt: Vị trí đắc địa của văn phòng này giúp bạn di chuyển thuận tiện đến các quận trung tâm khác của thành phố. Không chỉ tiết kiệm thời gian, mà còn tạo điều kiện tối ưu cho công việc kinh doanh và giao dịch với đối tác.",
                    "Thông Tin Văn Phòng:",
                    "Diện Tích Rộng Rãi: Với tổng diện tích lên đến 60m², văn phòng này rất rộng rãi, cho phép bạn tổ chức không gian làm việc theo ý muốn và tận dụng tối đa không gian.",
                    "️ Trang Bị Hiện Đại: Văn phòng đã được trang bị sẵn 2 máy lạnh, mang đến không gian làm việc thoải mái và mát mẻ, giúp bạn và đội ngũ làm việc duy trì năng suất cao.",
                    "Phù Hợp Mọi Quy Mô: Với diện tích và trang thiết bị hiện đại, văn phòng này rất lý tưởng cho việc kinh doanh và mở công ty, đáp ứng nhu cầu của các doanh nghiệp vừa và nhỏ. Bất kể bạn là một công ty mới thành lập hay một doanh nghiệp đang mở rộng, đây là nơi lý tưởng để bạn bắt đầu hoặc phát triển.",
                    "Giá Thuê Hấp Dẫn: Với giá thuê chỉ 6 triệu đồng/tháng",
                    "Địa Chỉ Văn Phòng Lý Tưởng: Văn phòng nằm tại địa chỉ 219B Nơ Trang Long, Phường 12, Quận Bình Thạnh. Vị trí thuận lợi đối diện với Liên Đoàn Lao Động và gần Hồ Bơi Li Đô, tạo nên một môi trường làm việc và kinh doanh đẳng cấp.",
                    "Liên Hệ Ngay Để Xem Văn Phòng Trực Tiếp:"
                ]
            },
            "overview": {
                "header": "Đặc điểm tin đăng",
                "content": [
                    {
                        "name": "Mã tin:",
                        "content": "#635199"
                    },
                    {
                        "name": "Khu vực",
                        "content": "Cho thuê mặt bằng, văn phòng Hồ Chí Minh"
                    },
                    {
                        "name": "Loại tin rao:",
                        "content": "Cho thuê mặt bằng, văn phòng"
                    },
                    {
                        "name": "Đối tượng thuê:",
                        "content": "Tất cả"
                    },
                    {
                        "name": "Gói tin:",
                        "content": "Tin thường"
                    },
                    {
                        "name": "Ngày đăng:",
                        "content": "Thứ 3, 10:44 12/09/2023"
                    },
                    {
                        "name": "Ngày hết hạn:",
                        "content": "Thứ 3, 10:44 19/09/2023"
                    }
                ]
            },
            "contact": {
                "header": "Thông tin liên hệ",
                "content": [
                    {
                        "name": "Liên hệ:",
                        "content": "Phạm Thị Thùy Dung"
                    },
                    {
                        "name": "Điện thoại:",
                        "content": "0792436464"
                    },
                    {
                        "name": "Zalo",
                        "content": "0792436464"
                    }
                ]
            }
        },
        {
            "images": [
                "https://pt123.cdn.static123.com/images/thumbs/900x600/fit/2023/09/12/z4521131497473-e7fdc9e4871be9735207d927dfcddcb1_1694487641.jpg",
                "https://pt123.cdn.static123.com/images/thumbs/900x600/fit/2023/09/12/z4685472516773-3f55ee1a91fd0b3fd4dd52a2084d1c53_1694487641.jpg",
                "https://pt123.cdn.static123.com/images/thumbs/900x600/fit/2023/09/12/z4685472600495-0b06949dfcd1249286a3b73add1a972d_1694487642.jpg",
                "https://pt123.cdn.static123.com/images/thumbs/900x600/fit/2023/09/12/z4521131490072-7bc3e7f16652c4781028a696fc677b87_1694487640.jpg",
                "https://pt123.cdn.static123.com/images/thumbs/900x600/fit/2023/09/12/z4521131490143-86b9b6d60cd9405ae4974bd8a9a12ec5_1694487640.jpg",
                "https://pt123.cdn.static123.com/images/thumbs/900x600/fit/2023/09/12/z4521131493257-4f1713658560ad72de6d4d20a1f3c0ad_1694487640.jpg",
                "https://pt123.cdn.static123.com/images/thumbs/900x600/fit/2023/09/12/z4521131493338-b86d039546a6dc45cf6da0b45f80ee9f_1694487640.jpg",
                "https://pt123.cdn.static123.com/images/thumbs/900x600/fit/2023/09/12/z4521131497473-e7fdc9e4871be9735207d927dfcddcb1_1694487641.jpg",
                "https://pt123.cdn.static123.com/images/thumbs/900x600/fit/2023/09/12/z4685472516773-3f55ee1a91fd0b3fd4dd52a2084d1c53_1694487641.jpg"
            ],
            "header": {
                "title": "Cho thuê 2 tầng văn phòng rộng rãi tại ngõ 198 Xã Đàn, Đống Đa",
                "class": {
                    "content": "Chuyên mục: Cho thuê mặt bằng, văn phòng Quận Đống Đa",
                    "classType": "Cho thuê mặt bằng, văn phòng Quận Đống Đa"
                },
                "address": "Địa chỉ: ngõ 198 Xã Đàn, Phường Kim Liên, Quận Đống Đa, Hà Nội",
                "attributes": {
                    "price": "25 triệu/tháng",
                    "acreage": "170m2",
                    "published": "12/09/2023",
                    "hashtag": "635193"
                }
            },
            "mainContent": {
                "header": "Thông tin mô tả",
                "content": [
                    "Cho thuê 2 tầng thông phòng làm Văn phòng lâu dài (mỗi tầng 85m2) mặt tiền 6,5m.",
                    "Tầng 1 để xe chung. Ngõ rộng 3 ô tô tránh.",
                    "Giao thông thuận tiện, đi 50m ra ngã tư Xã Đàn - Phạm Ngọc Thạch",
                    "LH: a Khải - 081.883.6222"
                ]
            },
            "overview": {
                "header": "Đặc điểm tin đăng",
                "content": [
                    {
                        "name": "Mã tin:",
                        "content": "#635193"
                    },
                    {
                        "name": "Khu vực",
                        "content": "Cho thuê mặt bằng, văn phòng Hà Nội"
                    },
                    {
                        "name": "Loại tin rao:",
                        "content": "Cho thuê mặt bằng, văn phòng"
                    },
                    {
                        "name": "Đối tượng thuê:",
                        "content": "Tất cả"
                    },
                    {
                        "name": "Gói tin:",
                        "content": "Tin thường"
                    },
                    {
                        "name": "Ngày đăng:",
                        "content": "Thứ 3, 10:01 12/09/2023"
                    },
                    {
                        "name": "Ngày hết hạn:",
                        "content": "Thứ 3, 10:01 26/09/2023"
                    }
                ]
            },
            "contact": {
                "header": "Thông tin liên hệ",
                "content": [
                    {
                        "name": "Liên hệ:",
                        "content": "Khải"
                    },
                    {
                        "name": "Điện thoại:",
                        "content": "0818836222"
                    },
                    {
                        "name": "Zalo",
                        "content": "0818836222"
                    }
                ]
            }
        },
        {
            "images": [
                "https://pt123.cdn.static123.com/images/thumbs/900x600/fit/2023/08/03/z4543822407612-006-ee24d31f6525712d6034812b99267fa3_1691034471.jpg",
                "https://pt123.cdn.static123.com/images/thumbs/900x600/fit/2023/08/03/0_1691034468.jpg",
                "https://pt123.cdn.static123.com/images/thumbs/900x600/fit/2023/08/03/1_1691034468.jpg",
                "https://pt123.cdn.static123.com/images/thumbs/900x600/fit/2023/08/03/z4543822407612-001-ec9dc61dbe49c5d6ca17cbee06a223b9_1691034469.jpg",
                "https://pt123.cdn.static123.com/images/thumbs/900x600/fit/2023/08/03/z4543822407612-002-994468789622812bf12b16b2c02bfb39_1691034469.jpg",
                "https://pt123.cdn.static123.com/images/thumbs/900x600/fit/2023/08/03/z4543822407612-003-1ff565d9bddc13183b3c6cb6be8f7916_1691034469.jpg",
                "https://pt123.cdn.static123.com/images/thumbs/900x600/fit/2023/08/03/z4543822407612-004-59fbae1864dbc28c1f9053c3ba758ee3_1691034470.jpg",
                "https://pt123.cdn.static123.com/images/thumbs/900x600/fit/2023/08/03/z4543822407612-006-ee24d31f6525712d6034812b99267fa3_1691034471.jpg",
                "https://pt123.cdn.static123.com/images/thumbs/900x600/fit/2023/08/03/0_1691034468.jpg"
            ],
            "header": {
                "title": "MBKD LỐI ĐI RIÊNG TRẦN THIỆN CHÁNH P12 Q10",
                "class": {
                    "content": "Chuyên mục: Cho thuê mặt bằng, văn phòng Quận 10",
                    "classType": "Cho thuê mặt bằng, văn phòng Quận 10"
                },
                "address": "Địa chỉ: 41 Trần Thiện Chánh, Phường 12, Quận 10, Hồ Chí Minh",
                "attributes": {
                    "price": "11 triệu/tháng",
                    "acreage": "36m2",
                    "published": "03/09/2023",
                    "hashtag": "632140"
                }
            },
            "mainContent": {
                "header": "Thông tin mô tả",
                "content": [
                    "MBKD mặt tiền 41 Trần Thiện Chánh - Q10",
                    "Diện tích 3x12m, đã ngăn lối đi riêng.",
                    "Giá 11tr (có thương lượng thiện chí)",
                    "Mặt tiền đường lớn 16m gần 3 Tháng 2, vỉa hè rộng rãi",
                    "Kinh doanh mọi ngành nghề (ko nấu ăn có mùi)",
                    "0559986720 - 0332422099"
                ]
            },
            "overview": {
                "header": "Đặc điểm tin đăng",
                "content": [
                    {
                        "name": "Mã tin:",
                        "content": "#632140"
                    },
                    {
                        "name": "Khu vực",
                        "content": "Cho thuê mặt bằng, văn phòng Hồ Chí Minh"
                    },
                    {
                        "name": "Loại tin rao:",
                        "content": "Cho thuê mặt bằng, văn phòng"
                    },
                    {
                        "name": "Đối tượng thuê:",
                        "content": "Tất cả"
                    },
                    {
                        "name": "Gói tin:",
                        "content": "Tin thường"
                    },
                    {
                        "name": "Ngày đăng:",
                        "content": "Chủ Nhật, 09:42 03/09/2023"
                    },
                    {
                        "name": "Ngày hết hạn:",
                        "content": "Thứ 3, 09:42 03/10/2023"
                    }
                ]
            },
            "contact": {
                "header": "Thông tin liên hệ",
                "content": [
                    {
                        "name": "Liên hệ:",
                        "content": "Phùng Nguyễn Hoàng Long"
                    },
                    {
                        "name": "Điện thoại:",
                        "content": "0979043780"
                    },
                    {
                        "name": "Zalo",
                        "content": "0979043780"
                    }
                ]
            }
        },
        {
            "images": [
                "https://pt123.cdn.static123.com/images/thumbs/900x600/fit/2023/08/01/img-20230731-084541_1690883911.jpg",
                "https://pt123.cdn.static123.com/images/thumbs/900x600/fit/2023/08/01/img-20230731-084547_1690883911.jpg",
                "https://pt123.cdn.static123.com/images/thumbs/900x600/fit/2023/08/01/img-20230731-084541_1690883911.jpg",
                "https://pt123.cdn.static123.com/images/thumbs/900x600/fit/2023/08/01/img-20230731-084547_1690883911.jpg"
            ],
            "header": {
                "title": "Cho thuê mặt bằng kd nhà thuốc hoặc kd tiệm tóc",
                "class": {
                    "content": "Chuyên mục: Cho thuê mặt bằng, văn phòng Quận 4",
                    "classType": "Cho thuê mặt bằng, văn phòng Quận 4"
                },
                "address": "Địa chỉ: Phường 14, Quận 4, Hồ Chí Minh",
                "attributes": {
                    "price": "12 triệu/tháng",
                    "acreage": "50m2",
                    "published": "1 ngày trước",
                    "hashtag": "631972"
                }
            },
            "mainContent": {
                "header": "Thông tin mô tả",
                "content": [
                    "Nhà cho thuê mặt bằng lầu trệt kd tiệm thuốc tây hoặc nha khoa ,hoặc kd spa tiệm tóc! Nhà mới xây dựng xong ! Khu vực rất sam uất! Nhà sạch sẽ và rất mới nên chỉ cho thuê những ai có nhu cầu kd các ngạnh nghề trên! Liên hệ chính chủ 0983635245"
                ]
            },
            "overview": {
                "header": "Đặc điểm tin đăng",
                "content": [
                    {
                        "name": "Mã tin:",
                        "content": "#631972"
                    },
                    {
                        "name": "Khu vực",
                        "content": "Cho thuê mặt bằng, văn phòng Hồ Chí Minh"
                    },
                    {
                        "name": "Loại tin rao:",
                        "content": "Cho thuê mặt bằng, văn phòng"
                    },
                    {
                        "name": "Đối tượng thuê:",
                        "content": "Tất cả"
                    },
                    {
                        "name": "Gói tin:",
                        "content": "Tin thường"
                    },
                    {
                        "name": "Ngày đăng:",
                        "content": "Chủ Nhật, 07:17 17/09/2023"
                    },
                    {
                        "name": "Ngày hết hạn:",
                        "content": "Thứ 2, 07:11 18/09/2023"
                    }
                ]
            },
            "contact": {
                "header": "Thông tin liên hệ",
                "content": [
                    {
                        "name": "Liên hệ:",
                        "content": "Ngô Tự Tráng"
                    },
                    {
                        "name": "Điện thoại:",
                        "content": "0983635245"
                    },
                    {
                        "name": "Zalo",
                        "content": "0983635245"
                    }
                ]
            }
        },
        {
            "images": [],
            "header": {
                "title": "Cho thuê Vị trí lắp đặt ATM tại tòa nhà CT Plaza Minh Châu, mặt tiền 369 Đường Lê Văn Sỹ, Quận 3, TP HCM",
                "class": {
                    "content": "Chuyên mục: Cho thuê mặt bằng, văn phòng Quận 3",
                    "classType": "Cho thuê mặt bằng, văn phòng Quận 3"
                },
                "address": "Địa chỉ: 369 Lê Văn Sỹ, Phường 12, Quận 3, Hồ Chí Minh",
                "attributes": {
                    "price": "1 triệu/tháng",
                    "acreage": "10m2",
                    "published": "13/09/2023",
                    "hashtag": "635361"
                }
            },
            "mainContent": {
                "header": "Thông tin mô tả",
                "content": [
                    "-VỊ TRÍ VÀNG LÕI TRUNG TÂM QUẬN 3, CT Plaza Minh Châu nằm trên con đường huyết mạch Quận 3 với mật độ cư dân đông đúc, kinh doanh mua bán, thời trang sầm uất bật nhất TP HCM.",
                    "-Giao thông thuận tiện, vừa có vỉa hè rộng nhất trên toàn tuyến đường, dễ dàng nhìn thấy ATM, đường 2 chiều, dễ tiếp cận giao dịch, dễ dàng trong việc tiếp quỹ, mát mẻ, có chỗ đậu xe rộng rãi thông thoáng cho khách hàng..",
                    "-Diện tích có thể đặt được 1 hoặc 2 máy ATM",
                    "-Cho thuê dài hạn, giá giá cả thương lượng",
                    "-Hotline Chủ đầu tư: 0908 496 945 (Mr Bình)"
                ]
            },
            "overview": {
                "header": "Đặc điểm tin đăng",
                "content": [
                    {
                        "name": "Mã tin:",
                        "content": "#635361"
                    },
                    {
                        "name": "Khu vực",
                        "content": "Cho thuê mặt bằng, văn phòng Hồ Chí Minh"
                    },
                    {
                        "name": "Loại tin rao:",
                        "content": "Cho thuê mặt bằng, văn phòng"
                    },
                    {
                        "name": "Đối tượng thuê:",
                        "content": "Tất cả"
                    },
                    {
                        "name": "Gói tin:",
                        "content": "Tin miễn phí"
                    },
                    {
                        "name": "Ngày đăng:",
                        "content": "Thứ 4, 17:32 13/09/2023"
                    },
                    {
                        "name": "Ngày hết hạn:",
                        "content": "Thứ 2, 17:32 18/09/2023"
                    }
                ]
            },
            "contact": {
                "header": "Thông tin liên hệ",
                "content": [
                    {
                        "name": "Liên hệ:",
                        "content": "Phạm Bình"
                    },
                    {
                        "name": "Điện thoại:",
                        "content": "0908496945"
                    },
                    {
                        "name": "Zalo",
                        "content": "0908496945"
                    }
                ]
            }
        },
        {
            "images": [
                "https://pt123.cdn.static123.com/images/thumbs/900x600/fit/2023/07/30/z4559736136358-868955484634d31d0ed7b7a6e353a836_1690698259.jpg",
                "https://pt123.cdn.static123.com/images/thumbs/900x600/fit/2023/07/30/z4559736101529-28e3564b7b4149f673395c0f27d7fa7d_1690698257.jpg",
                "https://pt123.cdn.static123.com/images/thumbs/900x600/fit/2023/07/30/z4559736124838-e22e93f918f5bb59508c5412fd5b7a89_1690698258.jpg",
                "https://pt123.cdn.static123.com/images/thumbs/900x600/fit/2023/07/30/z4559735968937-99f3c2fee3538d3a86629d7b2b533dd7_1690698245.jpg",
                "https://pt123.cdn.static123.com/images/thumbs/900x600/fit/2023/07/30/z4559735974002-76284088ad8e9afed15170c961e29c36_1690698245.jpg",
                "https://pt123.cdn.static123.com/images/thumbs/900x600/fit/2023/07/30/z4559735974139-f45d6dc22981850526ec27ddf2ef91e7_1690698247.jpg",
                "https://pt123.cdn.static123.com/images/thumbs/900x600/fit/2023/07/30/z4559735982216-e0ea8b6a7b57d4f17172833e38ab44a1_1690698248.jpg",
                "https://pt123.cdn.static123.com/images/thumbs/900x600/fit/2023/07/30/z4559735982868-c7027a617c15701f7fe0162ccfc9e5e2_1690698250.jpg",
                "https://pt123.cdn.static123.com/images/thumbs/900x600/fit/2023/07/30/z4559735988028-379c7170500eb3ee4eb0dbda249fec50_1690698250.jpg",
                "https://pt123.cdn.static123.com/images/thumbs/900x600/fit/2023/07/30/z4559735991816-4abe788ab99e380cd2413122581b3cd4_1690698252.jpg",
                "https://pt123.cdn.static123.com/images/thumbs/900x600/fit/2023/07/30/z4559735995134-de5e9028770df4617e77a2542616ebed_1690698253.jpg",
                "https://pt123.cdn.static123.com/images/thumbs/900x600/fit/2023/07/30/z4559735995918-18445f3bf449aa72a5017684015c912a_1690698254.jpg",
                "https://pt123.cdn.static123.com/images/thumbs/900x600/fit/2023/07/30/z4559735997296-2493aa59db4776948b02a7144f3aa557_1690698255.jpg",
                "https://pt123.cdn.static123.com/images/thumbs/900x600/fit/2023/07/30/z4559736136358-868955484634d31d0ed7b7a6e353a836_1690698259.jpg",
                "https://pt123.cdn.static123.com/images/thumbs/900x600/fit/2023/07/30/z4559736101529-28e3564b7b4149f673395c0f27d7fa7d_1690698257.jpg"
            ],
            "header": {
                "title": "Cho thuê nhà mới mặt phố thụy khuê 4 tầng 63 thụy khuê",
                "class": {
                    "content": "Chuyên mục: Cho thuê mặt bằng, văn phòng Quận Tây Hồ",
                    "classType": "Cho thuê mặt bằng, văn phòng Quận Tây Hồ"
                },
                "address": "Địa chỉ: 63 đường Thụy Khuê, Phường Thụy Khuê, Quận Tây Hồ, Hà Nội",
                "attributes": {
                    "price": "70 triệu/tháng",
                    "acreage": "100m2",
                    "published": "11/09/2023",
                    "hashtag": "631795"
                }
            },
            "mainContent": {
                "header": "Thông tin mô tả",
                "content": [
                    "Cho thuê nhà mới mặt phố thụy khuê 4 tầng",
                    "Diện tích T1,2,3,4 gần 100m2",
                    "Mặt tiền 5m, 2 mặt thoáng (1 mặt ngõ) 2 lối đi.",
                    "Tầng 1 có thể kinh doanh riêng lối đi riêng.",
                    "Gần chợ, trường học, chung cư, an ninh cao, thuận tiện kinh doanh nhiều dịch vụ, văn phòng và nhà ở.",
                    "Có chỗ đỗ xe số lượng lớn ô tô và xe máy.",
                    "Vệ sinh khép kín.",
                    "Giá thuê 70 tr (có thương lượng cho khách thuê lâu dài). Ưu tiên cho khách thuê toàn bộ 4 tầng.",
                    "[Album]"
                ]
            },
            "overview": {
                "header": "Đặc điểm tin đăng",
                "content": [
                    {
                        "name": "Mã tin:",
                        "content": "#631795"
                    },
                    {
                        "name": "Khu vực",
                        "content": "Cho thuê mặt bằng, văn phòng Hà Nội"
                    },
                    {
                        "name": "Loại tin rao:",
                        "content": "Cho thuê mặt bằng, văn phòng"
                    },
                    {
                        "name": "Đối tượng thuê:",
                        "content": "Tất cả"
                    },
                    {
                        "name": "Gói tin:",
                        "content": "Tin thường"
                    },
                    {
                        "name": "Ngày đăng:",
                        "content": "Thứ 2, 16:53 11/09/2023"
                    },
                    {
                        "name": "Ngày hết hạn:",
                        "content": "Thứ 7, 16:53 16/09/2023"
                    }
                ]
            },
            "contact": {
                "header": "Thông tin liên hệ",
                "content": [
                    {
                        "name": "Liên hệ:",
                        "content": "minh bắc"
                    },
                    {
                        "name": "Điện thoại:",
                        "content": "0862023934"
                    },
                    {
                        "name": "Zalo",
                        "content": "0862023934"
                    }
                ]
            }
        },
        {
            "images": [
                "https://pt123.cdn.static123.com/images/thumbs/900x600/fit/2023/09/06/z4659259045786-b4156596c9986a84c847ce0cba716bf4_1694013768.jpg",
                "https://pt123.cdn.static123.com/images/thumbs/900x600/fit/2023/09/06/z4659257542699-3dcd3ec6ef0096639a2e6b2dcf6c37e0_1694013744.jpg",
                "https://pt123.cdn.static123.com/images/thumbs/900x600/fit/2023/09/06/z4659257537862-b90ca22525f922a696d617f0101e6084_1694013744.jpg",
                "https://pt123.cdn.static123.com/images/thumbs/900x600/fit/2023/09/06/z4659257543047-35fb722b6f163b2b67e9bc4252afdb21_1694013748.jpg",
                "https://pt123.cdn.static123.com/images/thumbs/900x600/fit/2023/09/06/z4659257548656-d5eaa57f27e1d0a069a19dd8068fe4ac_1694013749.jpg",
                "https://pt123.cdn.static123.com/images/thumbs/900x600/fit/2023/09/06/z4659257554446-766f8011ab6173f494f5776e6147c331_1694013752.jpg",
                "https://pt123.cdn.static123.com/images/thumbs/900x600/fit/2023/09/06/z4659259015935-4d76baf86aaffc440f99b1fa7deff64f_1694013757.jpg",
                "https://pt123.cdn.static123.com/images/thumbs/900x600/fit/2023/09/06/z4659259019953-15c1b580281623c402a1f7b04631e828_1694013757.jpg",
                "https://pt123.cdn.static123.com/images/thumbs/900x600/fit/2023/09/06/z4659259023339-c898946dda17c971197654a515a38c2d_1694013762.jpg",
                "https://pt123.cdn.static123.com/images/thumbs/900x600/fit/2023/09/06/z4659259027527-25ad495adf50499582dc650fe58bac88_1694013762.jpg",
                "https://pt123.cdn.static123.com/images/thumbs/900x600/fit/2023/09/06/z4659259031249-b2c19840100a5cf356cf02bab3e88467_1694013765.jpg",
                "https://pt123.cdn.static123.com/images/thumbs/900x600/fit/2023/09/06/z4659259035406-5b681945ca51df9e965b61407103a4d4_1694013765.jpg",
                "https://pt123.cdn.static123.com/images/thumbs/900x600/fit/2023/09/06/z4659259041000-6beb9c3a9130d91f79e7a4d8a724217c_1694013767.jpg",
                "https://pt123.cdn.static123.com/images/thumbs/900x600/fit/2023/09/06/z4659259045786-b4156596c9986a84c847ce0cba716bf4_1694013768.jpg",
                "https://pt123.cdn.static123.com/images/thumbs/900x600/fit/2023/09/06/z4659257542699-3dcd3ec6ef0096639a2e6b2dcf6c37e0_1694013744.jpg"
            ],
            "header": {
                "title": "Cho thuê mặt bằng văn phòng và mặt bằng rooftop sân thượng chung 1 tòa nhà mặt tiền Trường Chinh - Tham Lương",
                "class": {
                    "content": "Chuyên mục: Cho thuê mặt bằng, văn phòng Quận 12",
                    "classType": "Cho thuê mặt bằng, văn phòng Quận 12"
                },
                "address": "Địa chỉ: Trường Chinh, Phường Tân Thới Nhất, Quận 12, Hồ Chí Minh",
                "attributes": {
                    "price": "10 triệu/tháng",
                    "acreage": "140m2",
                    "published": "11/09/2023",
                    "hashtag": "634766"
                }
            },
            "mainContent": {
                "header": "Thông tin mô tả",
                "content": [
                    "Cho thuê mặt bằng văn phòng và mặt bằng rooftop sân thượng chung 1 tòa nhà mặt tiền Trường Chinh - Tham Lương",
                    "Địa chỉ: 268 Trường Chinh, phường Đông Hưng Thuận, quận 12 - Kế bên cầu Tham Lương",
                    "Mặt bằng văn phòng mặt tiền Trường Chinh : 5m x 10m đã set up cơ bản hỗ trợ sơn sửa làm văn phòng rộng mà giá rẻ so với tt",
                    "Mặt bằng sân thượng rooftop cực rộng : 140m2 2 tầng riêng biệt đã set up cơ bản hỗ trợ sơn sửa phù hợp kinh doanh cf, ăn uống",
                    "Giá",
                    "Văn Phòng: 10tr",
                    "Rooftop 18tr",
                    "Vị trí tốt, đông dân cư, nhà sạch sẽ , thoáng, nhà mới,dọn vào kinh doanh ngay",
                    "Cọc: 2 tháng",
                    "Thời hạn thuê: 2-3 năm",
                    "️️Note: ưu tiên check in sớm - có thương lượng dễ dàng chốt",
                    "️Liên Hệ Quang Đạt Zalo: ***"
                ]
            },
            "overview": {
                "header": "Đặc điểm tin đăng",
                "content": [
                    {
                        "name": "Mã tin:",
                        "content": "#634766"
                    },
                    {
                        "name": "Khu vực",
                        "content": "Cho thuê mặt bằng, văn phòng Hồ Chí Minh"
                    },
                    {
                        "name": "Loại tin rao:",
                        "content": "Cho thuê mặt bằng, văn phòng"
                    },
                    {
                        "name": "Đối tượng thuê:",
                        "content": "Tất cả"
                    },
                    {
                        "name": "Gói tin:",
                        "content": "Tin thường"
                    },
                    {
                        "name": "Ngày đăng:",
                        "content": "Thứ 2, 12:25 11/09/2023"
                    },
                    {
                        "name": "Ngày hết hạn:",
                        "content": "Thứ 2, 22:22 11/09/2023"
                    }
                ]
            },
            "contact": {
                "header": "Thông tin liên hệ",
                "content": [
                    {
                        "name": "Liên hệ:",
                        "content": "Hà Quang Đạt"
                    },
                    {
                        "name": "Điện thoại:",
                        "content": "0708037035"
                    },
                    {
                        "name": "Zalo",
                        "content": "0708037035"
                    }
                ]
            }
        },
        {
            "images": [
                "https://pt123.cdn.static123.com/images/thumbs/900x600/fit/2023/04/17/64688879-edc4-4053-9376-a408db4c5513_1681748312.jpg",
                "https://pt123.cdn.static123.com/images/thumbs/900x600/fit/2023/04/17/9bf07375-ec59-4fd2-a855-f2f83f500c49_1681748311.jpg",
                "https://pt123.cdn.static123.com/images/thumbs/900x600/fit/2023/04/17/64688879-edc4-4053-9376-a408db4c5513_1681748312.jpg",
                "https://pt123.cdn.static123.com/images/thumbs/900x600/fit/2023/04/17/9bf07375-ec59-4fd2-a855-f2f83f500c49_1681748311.jpg"
            ],
            "header": {
                "title": "Cho thuê mặt bằng kèm nhà đường Nguyễn Tri Phương, đối diện cổng công viên 29/3, khu phố cơm niêu",
                "class": {
                    "content": "Chuyên mục: Cho thuê mặt bằng, văn phòng Quận Thanh Khê",
                    "classType": "Cho thuê mặt bằng, văn phòng Quận Thanh Khê"
                },
                "address": "Địa chỉ: 78 Nguyễn Tri Phương, Phường Chính Gián, Quận Thanh Khê, Đà Nẵng",
                "attributes": {
                    "price": "20.000 đồng/tháng",
                    "acreage": "300m2",
                    "published": "10/09/2023",
                    "hashtag": "622579"
                }
            },
            "mainContent": {
                "header": "Thông tin mô tả",
                "content": [
                    "Cho thuê 300m2 mặt bằng kèm nhà đường Nguyễn Tri Phương đối diện cổng công viên 29/3. Phía trước ngay làn rẻ chuyển làn rất tiện. Phố sầm uất khách du lịch ăn cơm niêu. Cho thuê lâu dài. Nhà có thể cải tạo hoặc đập để sử dụng hết mặt bằng",
                    "Inbox em ạ hoặc call 0905055886"
                ]
            },
            "overview": {
                "header": "Đặc điểm tin đăng",
                "content": [
                    {
                        "name": "Mã tin:",
                        "content": "#622579"
                    },
                    {
                        "name": "Khu vực",
                        "content": "Cho thuê mặt bằng, văn phòng Đà Nẵng"
                    },
                    {
                        "name": "Loại tin rao:",
                        "content": "Cho thuê mặt bằng, văn phòng"
                    },
                    {
                        "name": "Đối tượng thuê:",
                        "content": "Tất cả"
                    },
                    {
                        "name": "Gói tin:",
                        "content": "Tin thường"
                    },
                    {
                        "name": "Ngày đăng:",
                        "content": "Chủ Nhật, 14:43 10/09/2023"
                    },
                    {
                        "name": "Ngày hết hạn:",
                        "content": "Thứ 6, 14:43 15/09/2023"
                    }
                ]
            },
            "contact": {
                "header": "Thông tin liên hệ",
                "content": [
                    {
                        "name": "Liên hệ:",
                        "content": "Tram tran"
                    },
                    {
                        "name": "Điện thoại:",
                        "content": "0935180945"
                    },
                    {
                        "name": "Zalo",
                        "content": "0935180945"
                    }
                ]
            }
        },
        {
            "images": [
                "https://pt123.cdn.static123.com/images/thumbs/900x600/fit/2020/06/07/img-9652_1591508905.jpg",
                "https://pt123.cdn.static123.com/images/thumbs/900x600/fit/2020/06/07/img-9666_1591508915.jpg",
                "https://pt123.cdn.static123.com/images/thumbs/900x600/fit/2020/06/07/img-9665_1591508913.jpg",
                "https://pt123.cdn.static123.com/images/thumbs/900x600/fit/2020/06/07/img-9668_1591508922.jpg",
                "https://pt123.cdn.static123.com/images/thumbs/900x600/fit/2023/06/15/img-20230615-123022_1686808173.jpg",
                "https://pt123.cdn.static123.com/images/thumbs/900x600/fit/2023/06/15/img-20230615-123019_1686808173.jpg",
                "https://pt123.cdn.static123.com/images/thumbs/900x600/fit/2020/06/07/img-9654_1591508906.jpg",
                "https://pt123.cdn.static123.com/images/thumbs/900x600/fit/2020/06/07/img-9652_1591508905.jpg",
                "https://pt123.cdn.static123.com/images/thumbs/900x600/fit/2020/06/07/img-9666_1591508915.jpg"
            ],
            "header": {
                "title": "MẶT BẰNG CHO THUÊ 25m2 7.5TR/T TRUNG TÂM THẢO ĐIỀN QUẬN 2",
                "class": {
                    "content": "Chuyên mục: Cho thuê mặt bằng, văn phòng Quận 2",
                    "classType": "Cho thuê mặt bằng, văn phòng Quận 2"
                },
                "address": "Địa chỉ: 12 Đường số 42, Phường Thảo Điền, Quận 2, Hồ Chí Minh",
                "attributes": {
                    "price": "7.5 triệu/tháng",
                    "acreage": "25m2",
                    "published": "09/09/2023",
                    "hashtag": "304234"
                }
            },
            "mainContent": {
                "header": "Thông tin mô tả",
                "content": [
                    "Thông tin chi tiết: MẶT BẰNG CHO THUÊ NGAY MẶT TIỀN ĐƯỜNG 42 trung tâm Thảo Điền Q.2.",
                    "Diện tích: 25m2",
                    "Ưu điểm: - Mặt tiền đường rộng 2 ô tô chánh nhau thoải mái.",
                    "- Khu dân cư yên tĩnh, đậu xe máy, ô tô rộng rãi không ảnh hường người khác",
                    "- Trung tâm Thảo Điền nên rất sầm uất xung quanh nhiều quán coffee, quán ăn, Trung tâm thương mại, VP công ty.......",
                    "- Được thiết kế khung nhôm kính trong suốt sạch sẽ, sang trọng.",
                    "- Văn phòng đã được trang bị Máy lạnh mới cực kỳ tiết kiệm điện",
                    "Thích hợp: - Để làm văn phòng cty.",
                    "- Shop bán online.",
                    "- Tiệm nail.",
                    "- Nối Mi.",
                    "- Tiệm giặt ủi.",
                    "-Lớp học, gia sự......",
                    ".....................",
                    "Xem hình để biết chi tiết nhé.",
                    "Dịch vụ kèm theo:",
                    "- Dọn dẹp khu vực chung cầu thang, nhà xe, tuần 1 lần.",
                    "- Chỗ để xe miễn phí",
                    "- Vị trí thuận lợi 5p tới hầm Thủ Thiêm vào Q1.",
                    "- Xung quanh rất nhiều siêu thị mini, cửa hàng tiện ích, quán ăn, quán cafe, trung tâm thương mại, vô cùng tiện lợi.",
                    "- Gần trường đại học văn hóa TP.HCM cơ sở 1.",
                    "Đảm bảo tất cả đều là hình thật và thông tin thật.",
                    "Ưu tiên người thuê lâu dài từ 6 tháng trở lên.",
                    "Địa chỉ: 12 Đường 42, P. Thảo Điền, quận 2.",
                    "A. Nam: 0938.983.193 ( Chủ nhà )",
                    "Liên hệ trước khi xem phòng.",
                    "Miễn trung gian, mô giới."
                ]
            },
            "overview": {
                "header": "Đặc điểm tin đăng",
                "content": [
                    {
                        "name": "Mã tin:",
                        "content": "#304234"
                    },
                    {
                        "name": "Khu vực",
                        "content": "Cho thuê mặt bằng, văn phòng Hồ Chí Minh"
                    },
                    {
                        "name": "Loại tin rao:",
                        "content": "Cho thuê mặt bằng, văn phòng"
                    },
                    {
                        "name": "Đối tượng thuê:",
                        "content": "Tất cả"
                    },
                    {
                        "name": "Gói tin:",
                        "content": "Tin thường"
                    },
                    {
                        "name": "Ngày đăng:",
                        "content": "Thứ 7, 23:03 09/09/2023"
                    },
                    {
                        "name": "Ngày hết hạn:",
                        "content": "Thứ 5, 23:03 14/09/2023"
                    }
                ]
            },
            "contact": {
                "header": "Thông tin liên hệ",
                "content": [
                    {
                        "name": "Liên hệ:",
                        "content": "Pham Van Nam"
                    },
                    {
                        "name": "Điện thoại:",
                        "content": "0938983193"
                    },
                    {
                        "name": "Zalo",
                        "content": "0938983193"
                    }
                ]
            }
        },
        {
            "images": [
                "https://pt123.cdn.static123.com/images/thumbs/900x600/fit/2023/04/21/7ede1783-81c0-4691-8dba-1f28ffa6887f_1682074612.jpg",
                "https://pt123.cdn.static123.com/images/thumbs/900x600/fit/2023/04/21/82028dca-4ec0-458d-aa03-d4cb468a19cd_1682074610.jpg",
                "https://pt123.cdn.static123.com/images/thumbs/900x600/fit/2023/04/21/6b101f38-a456-4d35-9c42-3020367e566f_1682074610.jpg",
                "https://pt123.cdn.static123.com/images/thumbs/900x600/fit/2023/04/21/af230af2-d344-4a2c-84a9-216154f85d2b_1682074611.jpg",
                "https://pt123.cdn.static123.com/images/thumbs/900x600/fit/2023/04/21/3d82dad7-c494-43d9-a7ac-3fcb64665381_1682074610.jpg",
                "https://pt123.cdn.static123.com/images/thumbs/900x600/fit/2023/04/21/92910849-56cf-45ae-a8f4-b6e1fe176206_1682074610.jpg",
                "https://pt123.cdn.static123.com/images/thumbs/900x600/fit/2023/04/21/74ec8c04-e98c-4915-8030-b6255233c277_1682074611.jpg",
                "https://pt123.cdn.static123.com/images/thumbs/900x600/fit/2023/04/21/06aac5f6-6a01-4959-9bb6-8ffdb42612ea_1682074611.jpg",
                "https://pt123.cdn.static123.com/images/thumbs/900x600/fit/2023/04/21/fa787127-8ab2-4755-9caf-43ad22d9ef71_1682074611.jpg",
                "https://pt123.cdn.static123.com/images/thumbs/900x600/fit/2023/04/21/fd12c8c9-fa83-43a7-a71c-1a1901dcbe25_1682074612.jpg",
                "https://pt123.cdn.static123.com/images/thumbs/900x600/fit/2023/04/21/dc44876e-7dc6-4d7e-a26e-69cc38190907_1682074612.jpg",
                "https://pt123.cdn.static123.com/images/thumbs/900x600/fit/2023/04/21/7ede1783-81c0-4691-8dba-1f28ffa6887f_1682074612.jpg",
                "https://pt123.cdn.static123.com/images/thumbs/900x600/fit/2023/04/21/82028dca-4ec0-458d-aa03-d4cb468a19cd_1682074610.jpg"
            ],
            "header": {
                "title": "Mặt bằng tầng trệt phố tập đoàn lớn,văn phòng công ty ,địa điểm kinh doanh đa ngành nghề.",
                "class": {
                    "content": "Chuyên mục: Cho thuê mặt bằng, văn phòng Quận 2",
                    "classType": "Cho thuê mặt bằng, văn phòng Quận 2"
                },
                "address": "Địa chỉ: 47 Phố số 56, Phường Bình Trưng Đông, Quận 2, Hồ Chí Minh",
                "attributes": {
                    "price": "15 triệu/tháng",
                    "acreage": "150m2",
                    "published": "08/09/2023",
                    "hashtag": "622995"
                }
            },
            "mainContent": {
                "header": "Thông tin mô tả",
                "content": [
                    "Mặt bằng rộng tại tầng trệt ngay mặt đường lớn ,tập trung nhiều tập đoàn ,phố văn phòng công ty,kinh doanh ngành nghề nào cũng thuận tiện và dễ dàng thành công (ngang 6* dài 25) diện tích tha hồ rộng rãi.",
                    "Xung quanh nhà còn có nhiều bãi đất trống ,đường rộng đậu xe vô tư ."
                ]
            },
            "overview": {
                "header": "Đặc điểm tin đăng",
                "content": [
                    {
                        "name": "Mã tin:",
                        "content": "#622995"
                    },
                    {
                        "name": "Khu vực",
                        "content": "Cho thuê mặt bằng, văn phòng Hồ Chí Minh"
                    },
                    {
                        "name": "Loại tin rao:",
                        "content": "Cho thuê mặt bằng, văn phòng"
                    },
                    {
                        "name": "Đối tượng thuê:",
                        "content": "Tất cả"
                    },
                    {
                        "name": "Gói tin:",
                        "content": "Tin thường"
                    },
                    {
                        "name": "Ngày đăng:",
                        "content": "Thứ 6, 15:40 08/09/2023"
                    },
                    {
                        "name": "Ngày hết hạn:",
                        "content": "Thứ 4, 15:40 13/09/2023"
                    }
                ]
            },
            "contact": {
                "header": "Thông tin liên hệ",
                "content": [
                    {
                        "name": "Liên hệ:",
                        "content": "Chị Phương"
                    },
                    {
                        "name": "Điện thoại:",
                        "content": "0963159439"
                    },
                    {
                        "name": "Zalo",
                        "content": "0963159439"
                    }
                ]
            }
        }
    ]
}